dnsmock/__init__.py
dnsmock/lib.py
dnsmock/version.py
dnsmock-21.2b2.dist-info/LICENSE
dnsmock-21.2b2.dist-info/METADATA
dnsmock-21.2b2.dist-info/WHEEL
dnsmock-21.2b2.dist-info/top_level.txt
dnsmock-21.2b2.dist-info/RECORD
