Metadata-Version: 2.1
Name: dnsmock
Version: 21.2b2
Summary: Python custom resolver
Home-page: https://github.com/imjoseangel/dnsmock
Author: Jose Angel Munoz
Author-email: josea.munoz@gmail.com
License: MIT
Keywords: dns resolver socket
Platform: UNKNOWN
Classifier: Development Status :: 4 - Beta
Classifier: Environment :: Console
Classifier: Intended Audience :: Developers
Classifier: License :: OSI Approved :: MIT License
Classifier: Programming Language :: Python :: 3
Classifier: Topic :: Terminals
Classifier: Topic :: Utilities
License-File: LICENSE
